stark/__init__.py
stark/app.py
stark/args.py
stark/cli.py
stark/constants.py
stark/password.py
stark/validation.py
stark-0.1.1.dist-info/LICENSE
stark-0.1.1.dist-info/METADATA
stark-0.1.1.dist-info/WHEEL
stark-0.1.1.dist-info/entry_points.txt
stark-0.1.1.dist-info/top_level.txt
stark-0.1.1.dist-info/RECORD
