Metadata-Version: 2.1
Name: stark
Version: 0.1.1
Summary: stark generates random and strong passwords
Home-page: https://github.com/Iheb-Haboubi/stark
Author: Iheb Haboubi
Author-email: iheb.haboubi56@gmail.com
License: MIT
Download-URL: https://github.com/Iheb-Haboubi/stark/tarball/0.0.1
Keywords: password,random,generator
Platform: UNKNOWN
Classifier: Programming Language :: Python :: 3.6
Classifier: Programming Language :: Python :: 3.7
Classifier: Programming Language :: Python :: 3.8
Classifier: Operating System :: OS Independent
Requires-Python: >=3.6
